Compiled from "IntegerTest.java"
public class spike.IntegerTest {
  public spike.IntegerTest();
    Code:
       0: aload_0       
       1: invokespecial #1                  // Method java/lang/Object."<init>":()V
       4: return        

  public static void main(java.lang.String[]);
    Code:
       0: iconst_4      
       1: invokestatic  #2                  // Method java/lang/Integer.valueOf:(I)Ljava/lang/Integer;
       4: astore_1      
       5: iconst_0      
       6: invokestatic  #2                  // Method java/lang/Integer.valueOf:(I)Ljava/lang/Integer;
       9: astore_2      
      10: aload_2       
      11: invokevirtual #3                  // Method java/lang/Integer.intValue:()I
      14: aload_2       
      15: invokevirtual #3                  // Method java/lang/Integer.intValue:()I
      18: isub          
      19: invokestatic  #2                  // Method java/lang/Integer.valueOf:(I)Ljava/lang/Integer;
      22: astore_3      
      23: return        
}
